rtadubai/JourneyPlanner.py
rtadubai/Nol.py
rtadubai/Salik.py
rtadubai/Shail.py
rtadubai/__init__.py
rtadubai/rta_captcha.py
rtadubai-0.1.5.dist-info/LICENSE
rtadubai-0.1.5.dist-info/METADATA
rtadubai-0.1.5.dist-info/WHEEL
rtadubai-0.1.5.dist-info/top_level.txt
rtadubai-0.1.5.dist-info/RECORD
