Metadata-Version: 2.1
Name: rtadubai
Version: 0.1.5
Summary: Unofficial API for RTA Dubai
Home-page: https://github.com/NotNalin/rtadubai
Author: NotNalin
Project-URL: Bug Tracker, https://github.com/NotNalin/rtadubai/issues
Classifier: Development Status :: 4 - Beta
Classifier: Programming Language :: Python :: 3
Classifier: License :: OSI Approved :: MIT License
Classifier: Operating System :: OS Independent
Requires-Python: >=3.8
License-File: LICENSE
Requires-Dist: requests
Requires-Dist: BeautifulSoup4
